MANIFEST.in
Makefile
README
setup.py
test/test_basic.py
tiddlywebplugins/__init__.py
tiddlywebplugins/pathinfohack.py
tiddlywebplugins.pathinfohack.egg-info/PKG-INFO
tiddlywebplugins.pathinfohack.egg-info/SOURCES.txt
tiddlywebplugins.pathinfohack.egg-info/dependency_links.txt
tiddlywebplugins.pathinfohack.egg-info/namespace_packages.txt
tiddlywebplugins.pathinfohack.egg-info/not-zip-safe
tiddlywebplugins.pathinfohack.egg-info/requires.txt
tiddlywebplugins.pathinfohack.egg-info/top_level.txt