Metadata-Version: 1.0
Name: tiddlywebplugins.pathinfohack
Version: 1.0.0
Summary: A TiddlyWeb plugin providing support for / in entity names under path info decoding web servers.
Home-page: http://pypi.python.org/pypi/tiddlywebplugins.pathinfohack
Author: Oveek
Author-email: tiddlyweb@peermore.com
License: UNKNOWN
Platform: Posix; MacOS X; Windows
